sqlmapcli/__init__.py
sqlmapcli/client.py
sqlmapcli/exceptions.py
sqlmapcli/logs.py
sqlmapcli/task.py
sqlmapcli-0.10.dist-info/DESCRIPTION.rst
sqlmapcli-0.10.dist-info/METADATA
sqlmapcli-0.10.dist-info/RECORD
sqlmapcli-0.10.dist-info/WHEEL
sqlmapcli-0.10.dist-info/metadata.json
sqlmapcli-0.10.dist-info/top_level.txt
